tsum/__init__.py
tsum/benefit.py
tsum/coverage.py
tsum/expand.py
tsum/local_expansion.py
tsum/log.py
tsum/model.py
tsum/overhead.py
tsum/pattern_marshalling.py
tsum/residue.py
tsum/saving.py
tsum/util.py
tsum-0.1.0.dist-info/LICENSE.txt
tsum-0.1.0.dist-info/METADATA
tsum-0.1.0.dist-info/WHEEL
tsum-0.1.0.dist-info/RECORD
