Metadata-Version: 2.1
Name: tsum
Version: 0.1.0
Summary: Summarize data in Dask DataFrames.
Author: Fasih Khatib
Author-email: hellofasih.confound928@passinbox.com
Requires-Python: >=3.9,<4.0
Classifier: Programming Language :: Python :: 3
Classifier: Programming Language :: Python :: 3.9
Classifier: Programming Language :: Python :: 3.10
Classifier: Programming Language :: Python :: 3.11
Classifier: Programming Language :: Python :: 3.12
Requires-Dist: attrs (>=23.2.0,<24.0.0)
Requires-Dist: cattrs (>=23.2.3,<24.0.0)
Requires-Dist: dask[dataframe,distributed] (>=2024.4.1,<2025.0.0)
Requires-Dist: frozendict (>=2.4.1,<3.0.0)
